<?xml version="1.0"?>
<!-- 	All string/array/plural names in this file are untranslateable.
	These strings only take space or mess something up. These strings can be removed.

	This file uses a specific format
	- First the application name: This must be the exact same name as the application in the language repository
	- Second the file type
	- Third the actual name of the string
	This format prevents that strings get mixed up and will spare time while doing the initial check.

	Please keep the applications and file types in alfabetical order, to keep the overview. -->
<resources>
	<item folder="all" application="AuthManager.apk" file="strings.xml" name="static_cache_db_md5"/>
	<item folder="all" application="Backup.apk" file="strings.xml" name="digit_percent"/>
	<item folder="all" application="Backup.apk" file="strings.xml" name="xiaomi_account_type"/>
	<item folder="all" application="Backup.apk" file="strings.xml" name="xiaomi_bytes_unit"/>
	<item folder="all" application="Backup.apk" file="strings.xml" name="xiaomi_kilobytes_unit"/>
	<item folder="all" application="Backup.apk" file="strings.xml" name="xiaomi_megabytes_unit"/>
	<item folder="all" application="Browser.apk" file="arrays.xml" name="baidu_in_list"/>
	<item folder="all" application="Browser.apk" file="arrays.xml" name="bing_in_list"/>
	<item folder="all" application="Browser.apk" file="arrays.xml" name="bing_zh_CN_in_list"/>
	<item folder="all" application="Browser.apk" file="arrays.xml" name="bookmarks_zh"/>
	<item folder="all" application="Browser.apk" file="arrays.xml" name="dianping_in_list"/>
	<item folder="all" application="Browser.apk" file="arrays.xml" name="easou_in_list"/>
	<item folder="all" application="Browser.apk" file="arrays.xml" name="google_in_list"/>
	<item folder="all" application="Browser.apk" file="arrays.xml" name="readmode_theme_bgcolors"/>
	<item folder="all" application="Browser.apk" file="arrays.xml" name="readmode_theme_fontcolors"/>
	<item folder="all" application="Browser.apk" file="arrays.xml" name="readmode_title_font_size"/>
	<item folder="all" application="Browser.apk" file="arrays.xml" name="s139_in_list"/>
	<item folder="all" application="Browser.apk" file="arrays.xml" name="shipin_in_list"/>
	<item folder="all" application="Browser.apk" file="arrays.xml" name="sogou_in_list"/>
	<item folder="all" application="Browser.apk" file="arrays.xml" name="taobao_in_list"/>
	<item folder="all" application="Browser.apk" file="arrays.xml" name="tupian_in_list"/>
	<item folder="all" application="Browser.apk" file="arrays.xml" name="yahoo_in_list"/>
	<item folder="all" application="Browser.apk" file="arrays.xml" name="yicha_in_list"/>
	<item folder="all" application="Browser.apk" file="strings.xml" name="common_use_phrase_bottom_bar_com_txt"/>
	<item folder="all" application="Browser.apk" file="strings.xml" name="common_use_phrase_bottom_bar_https_txt"/>
	<item folder="all" application="Browser.apk" file="strings.xml" name="common_use_phrase_bottom_bar_net_txt"/>
	<item folder="all" application="Browser.apk" file="strings.xml" name="common_use_phrase_bottom_bar_org_txt"/>
	<item folder="all" application="Browser.apk" file="strings.xml" name="common_use_phrase_bottom_bar_point_txt"/>
	<item folder="all" application="Browser.apk" file="strings.xml" name="common_use_phrase_bottom_bar_slash_txt"/>
	<item folder="all" application="Browser.apk" file="strings.xml" name="common_use_phrase_bottom_bar_www_txt"/>
	<item folder="all" application="BugReport.apk" file="strings.xml" name="pic_view_format"/>
	<item folder="all" application="Calculator.apk" file="strings.xml" name="xiaomi_bytes_unit"/>
	<item folder="all" application="Calculator.apk" file="strings.xml" name="xiaomi_kilobytes_unit"/>
	<item folder="all" application="Calculator.apk" file="strings.xml" name="xiaomi_megabytes_unit"/>
	<item folder="all" application="Calendar.apk" file="strings.xml" name="prefDefault_alerts_vibrate_false"/>
	<item folder="all" application="Calendar.apk" file="strings.xml" name="prefDefault_alerts_vibrate_true"/>
	<item folder="all" application="Calendar.apk" file="strings.xml" name="prefDefault_alerts_vibrateWhen"/>
	<item folder="all" application="CleanMaster.apk" file="strings.xml" name="preference_category_information_setting"/>
	<item folder="all" application="CleanMaster.apk" file="strings.xml" name="preference_category_key_auto_update_cleanup_db"/>
	<item folder="all" application="CleanMaster.apk" file="strings.xml" name="preference_key_information_setting_close"/>
	<item folder="all" application="CleanMaster.apk" file="strings.xml" name="preference_key_information_setting_wlan"/>
	<item folder="all" application="CloudBackup.apk" file="strings.xml" name="xiaomi_account_type"/>
	<item folder="all" application="CloudService.apk" file="strings.xml" name="find_device_dspt_provision_2"/>
	<item folder="all" application="CloudService.apk" file="strings.xml" name="find_device_dspt_provision_2_int"/>
	<item folder="all" application="CloudService.apk" file="strings.xml" name="find_device_notice_p2"/>
	<item folder="all" application="CloudService.apk" file="strings.xml" name="ks_key_download_button"/>
	<item folder="all" application="CloudService.apk" file="strings.xml" name="ks_key_status"/>
	<item folder="all" application="CloudService.apk" file="strings.xml" name="ks_key_udpate_time"/>
	<item folder="all" application="CloudService.apk" file="strings.xml" name="ks_key_version"/>
	<item folder="all" application="CloudService.apk" file="strings.xml" name="micloud_find_device_opened_content_url"/>
	<item folder="all" application="CloudService.apk" file="strings.xml" name="micloud_find_device_opened_content_url_int"/>
	<item folder="all" application="CloudService.apk" file="strings.xml" name="sync_dspt_provision2"/>
	<item folder="all" application="CloudService.apk" file="strings.xml" name="sync_dspt_provision2_int"/>
	<item folder="all" application="CloudService.apk" file="strings.xml" name="xiaomi_account_type"/>
	<item folder="all" application="Contacts.apk" file="strings.xml" name="call_type_and_date"/>
	<item folder="all" application="Contacts.apk" file="strings.xml" name="config_export_vcard_type"/>
	<item folder="all" application="Contacts.apk" file="strings.xml" name="config_import_vcard_type"/>
	<item folder="all" application="Contacts.apk" file="strings.xml" name="from_account_format"/>
	<item folder="all" application="Contacts.apk" file="strings.xml" name="import_weibo_progress_percent"/>
	<item folder="all" application="Contacts.apk" file="strings.xml" name="percent_sign"/>
	<item folder="all" application="Contacts.apk" file="strings.xml" name="percentage"/>
	<item folder="all" application="Contacts.apk" file="strings.xml" name="smart_group_action_bar_title"/>
	<item folder="all" application="Contacts.apk" file="strings.xml" name="widget_name_and_phonetic"/>
	<item folder="all" application="DeskClock.apk" file="arrays.xml" name="battery_charging_level"/>
	<item folder="all" application="DeskClock.apk" file="arrays.xml" name="cities_id_miui"/>
	<item folder="all" application="DeskClock.apk" file="arrays.xml" name="cities_names_miui"/>
	<item folder="all" application="DeskClock.apk" file="arrays.xml" name="cities_tz_miui"/>
	<item folder="all" application="DeskClock.apk" file="strings.xml" name="skip_alarm_date_format"/>
	<item folder="all" application="DocumentsUI.apk" file="strings.xml" name="character_counter_pattern"/>
	<item folder="all" application="DownloadProviderUi.apk" file="strings.xml" name="app_size"/>
	<item folder="all" application="DownloadProviderUi.apk" file="strings.xml" name="download_num_size"/>
	<item folder="all" application="DownloadProviderUi.apk" file="strings.xml" name="xunlei_brand_url"/>
	<item folder="all" application="Email.apk" file="strings.xml" name="application_mime_type"/>
	<item folder="all" application="Email.apk" file="strings.xml" name="account_cache_provider"/>
	<item folder="all" application="Email.apk" file="strings.xml" name="bank_card_list_card_num_fmt"/>
	<item folder="all" application="Email.apk" file="strings.xml" name="bcc"/>
	<item folder="all" application="Email.apk" file="strings.xml" name="bcc_heading"/>
	<item folder="all" application="Email.apk" file="strings.xml" name="cc"/>
	<item folder="all" application="Email.apk" file="strings.xml" name="cc_attribution"/>
	<item folder="all" application="Email.apk" file="strings.xml" name="cc_bcc"/>
	<item folder="all" application="Email.apk" file="strings.xml" name="conversation_content_provider"/>
	<item folder="all" application="Email.apk" file="strings.xml" name="eas_hotmail_email"/>
	<item folder="all" application="Email.apk" file="strings.xml" name="eas_outlook_email"/>
	<item folder="all" application="Email.apk" file="strings.xml" name="eas_template"/>
	<item folder="all" application="Email.apk" file="strings.xml" name="eml_attachment_provider"/>
	<item folder="all" application="Email.apk" file="strings.xml" name="formatted_subject"/>
	<item folder="all" application="Email.apk" file="strings.xml" name="forward_subject_label"/>
	<item folder="all" application="Email.apk" file="strings.xml" name="label_notification_ticker"/>
	<item folder="all" application="Email.apk" file="strings.xml" name="mailbox_name_server_all_unread"/>
	<item folder="all" application="Email.apk" file="strings.xml" name="mailbox_name_server_drafts"/>
	<item folder="all" application="Email.apk" file="strings.xml" name="mailbox_name_server_inbox"/>
	<item folder="all" application="Email.apk" file="strings.xml" name="mailbox_name_server_junk"/>
	<item folder="all" application="Email.apk" file="strings.xml" name="mailbox_name_server_outbox"/>
	<item folder="all" application="Email.apk" file="strings.xml" name="mailbox_name_server_sent"/>
	<item folder="all" application="Email.apk" file="strings.xml" name="mailbox_name_server_starred"/>
	<item folder="all" application="Email.apk" file="strings.xml" name="mailbox_name_server_trash"/>
	<item folder="all" application="Email.apk" file="strings.xml" name="prefDefault_autoAdvance"/>
	<item folder="all" application="Email.apk" file="strings.xml" name="reply_subject_label"/>
	<item folder="all" application="Email.apk" file="strings.xml" name="report_rendering_improvement"/>
	<item folder="all" application="Email.apk" file="strings.xml" name="report_rendering_improvement_desc"/>
	<item folder="all" application="Email.apk" file="strings.xml" name="report_rendering_problem"/>
	<item folder="all" application="Email.apk" file="strings.xml" name="report_rendering_problem_desc"/>
	<item folder="all" application="Email.apk" file="strings.xml" name="single_new_message_notification_title"/>
	<item folder="all" application="Email.apk" file="strings.xml" name="to"/>
	<item folder="all" application="Email.apk" file="strings.xml" name="trigger_compose_char"/>
	<item folder="all" application="Email.apk" file="strings.xml" name="trigger_refresh_char"/>
	<item folder="all" application="Email.apk" file="strings.xml" name="trigger_y_char"/>
	<item folder="all" application="Email.apk" file="strings.xml" name="wait_help_context"/>
	<item folder="all" application="Email.apk" file="strings.xml" name="widget_provider"/>
	<item folder="all" application="FileExplorer.apk" file="strings.xml" name="directory_info_divider"/>
	<item folder="all" application="FileExplorer.apk" file="strings.xml" name="fileSizeSuffix"/>
	<item folder="all" application="FileExplorer.apk" file="strings.xml" name="message_my_received_praise_count"/>
	<item folder="all" application="FileExplorer.apk" file="strings.xml" name="message_reply_suffix"/>
	<item folder="all" application="FileExplorer.apk" file="strings.xml" name="origin_name"/>
	<item folder="all" application="FileExplorer.apk" file="strings.xml" name="recommend_users"/>
	<item folder="all" application="FileExplorer.apk" file="strings.xml" name="search_statistic_match_invalid"/>
	<item folder="all" application="FileExplorer.apk" file="strings.xml" name="search_statistic_match_valid"/>
	<item folder="all" application="FileExplorer.apk" file="strings.xml" name="video_upload_item_title"/>
	<item folder="all" application="FindDevice.apk" file="strings.xml" name="find_device_notice_p2"/>
	<item folder="all" application="framework-res.apk" file="arrays.xml" name="config_statusBarIcons"/>
	<item folder="all" application="framework-res.apk" file="strings.xml" name="db_default_journal_mode"/>
	<item folder="all" application="framework-res.apk" file="strings.xml" name="db_default_sync_mode"/>
	<item folder="all" application="framework-res.apk" file="strings.xml" name="db_wal_sync_mode"/>
	<item folder="all" application="framework-res.apk" file="strings.xml" name="fileSizeSuffix"/>
	<item folder="all" application="framework-res.apk" file="strings.xml" name="network_available_sign_in_detailed"/>
	<item folder="all" application="framework-res.apk" file="strings.xml" name="notification_messaging_title_template"/>
	<item folder="all" application="framework-res.apk" file="strings.xml" name="zen_mode_rule_name_combination"/>
	<item folder="all" application="InCallUI.apk" file="arrays.xml" name="absent_num"/>
	<item folder="all" application="InCallUI.apk" file="strings.xml" name="antispam_marked_title"/>
	<item folder="all" application="MiDrive.apk" file="strings.xml" name="download_current_progress"/>
	<item folder="all" application="MiDrive.apk" file="strings.xml" name="fileSizeSuffix"/>
	<item folder="all" application="MiDrop.apk" file="strings.xml" name="action_bonjour"/>
	<item folder="all" application="MiDrop.apk" file="strings.xml" name="action_p2pgo"/>
	<item folder="all" application="MiDrop.apk" file="strings.xml" name="action_p2pls"/>
	<item folder="all" application="MiDrop.apk" file="strings.xml" name="hello_world"/>
	<item folder="all" application="MiDrop.apk" file="strings.xml" name="title_activity_bonjour"/>
	<item folder="all" application="MiDrop.apk" file="strings.xml" name="title_activity_intro"/>
	<item folder="all" application="MiDrop.apk" file="strings.xml" name="title_activity_main"/>
	<item folder="all" application="MiDrop.apk" file="strings.xml" name="title_activity_p2p_group_client"/>
	<item folder="all" application="MiDrop.apk" file="strings.xml" name="title_activity_p2p_group_owner"/>
	<item folder="all" application="MiDrop.apk" file="strings.xml" name="title_activity_p2p_legacy_station"/>
	<item folder="all" application="MiDrop.apk" file="strings.xml" name="title_activity_reception"/>
	<item folder="all" application="miui.apk" file="strings.xml" name="size_suffix"/>
	<item folder="all" application="MiuiBluetooth.apk" file="strings.xml" name="ble_profile_1"/>
	<item folder="all" application="MiuiBluetooth.apk" file="strings.xml" name="ble_profile_2"/>
	<item folder="all" application="MiuiCamera.apk" file="strings.xml" name="camera_face_beauty_default"/>
	<item folder="all" application="MiuiCamera.apk" file="strings.xml" name="camera_face_beauty_simple_mode_close"/>
	<item folder="all" application="MiuiCamera.apk" file="strings.xml" name="camera_face_beauty_simple_mode_open"/>
	<item folder="all" application="MiuiCamera.apk" file="strings.xml" name="pref_audio_focus_default"/>
	<item folder="all" application="MiuiCamera.apk" file="strings.xml" name="pref_audio_focus_entryvalue_front"/>
	<item folder="all" application="MiuiCamera.apk" file="strings.xml" name="pref_audio_focus_entryvalue_general"/>
	<item folder="all" application="MiuiCamera.apk" file="strings.xml" name="pref_audio_focus_entryvalue_rear"/>
	<item folder="all" application="MiuiCamera.apk" file="strings.xml" name="pref_audio_indicator_entryvalue_default"/>
	<item folder="all" application="MiuiCamera.apk" file="strings.xml" name="pref_audio_indicator_entryvalue_off"/>
	<item folder="all" application="MiuiCamera.apk" file="strings.xml" name="pref_audio_indicator_entryvalue_on"/>
	<item folder="all" application="MiuiCamera.apk" file="strings.xml" name="pref_camera_ae_bracket_hdr_default"/>
	<item folder="all" application="MiuiCamera.apk" file="strings.xml" name="pref_camera_antibanding_60"/>
	<item folder="all" application="MiuiCamera.apk" file="strings.xml" name="pref_camera_antibanding_default"/>
	<item folder="all" application="MiuiCamera.apk" file="strings.xml" name="pref_camera_audioencoder_default"/>
	<item folder="all" application="MiuiCamera.apk" file="strings.xml" name="pref_camera_autoexposure_default"/>
	<item folder="all" application="MiuiCamera.apk" file="strings.xml" name="pref_camera_autoexposure_value_centerweighted"/>
	<item folder="all" application="MiuiCamera.apk" file="strings.xml" name="pref_camera_autoexposure_value_frameaverage"/>
	<item folder="all" application="MiuiCamera.apk" file="strings.xml" name="pref_camera_autoexposure_value_spotmetering"/>
	<item folder="all" application="MiuiCamera.apk" file="strings.xml" name="pref_camera_coloreffect_default"/>
	<item folder="all" application="MiuiCamera.apk" file="strings.xml" name="pref_camera_contrast_default"/>
	<item folder="all" application="MiuiCamera.apk" file="strings.xml" name="pref_camera_countdown_default"/>
	<item folder="all" application="MiuiCamera.apk" file="strings.xml" name="pref_camera_delay_capture_default"/>
	<item folder="all" application="MiuiCamera.apk" file="strings.xml" name="pref_camera_denoise_default"/>
	<item folder="all" application="MiuiCamera.apk" file="strings.xml" name="pref_camera_exposuretime_default"/>
	<item folder="all" application="MiuiCamera.apk" file="strings.xml" name="pref_camera_facedetection_default"/>
	<item folder="all" application="MiuiCamera.apk" file="strings.xml" name="pref_camera_flashmode_default"/>
	<item folder="all" application="MiuiCamera.apk" file="strings.xml" name="pref_camera_focusmode_value_default"/>
	<item folder="all" application="MiuiCamera.apk" file="strings.xml" name="pref_camera_front_picture_size_default"/>
	<item folder="all" application="MiuiCamera.apk" file="strings.xml" name="pref_camera_front_picture_size_default_hm2"/>
	<item folder="all" application="MiuiCamera.apk" file="strings.xml" name="pref_camera_front_picture_size_default_hm2a"/>
	<item folder="all" application="MiuiCamera.apk" file="strings.xml" name="pref_camera_front_picture_size_default_hm2s"/>
	<item folder="all" application="MiuiCamera.apk" file="strings.xml" name="pref_camera_front_picture_size_default_hm3"/>
	<item folder="all" application="MiuiCamera.apk" file="strings.xml" name="pref_camera_front_picture_size_default_m4w"/>
	<item folder="all" application="MiuiCamera.apk" file="strings.xml" name="pref_camera_hdr_entryvalue_auto"/>
	<item folder="all" application="MiuiCamera.apk" file="strings.xml" name="pref_camera_hdr_entryvalue_live"/>
	<item folder="all" application="MiuiCamera.apk" file="strings.xml" name="pref_camera_hdr_entryvalue_normal"/>
	<item folder="all" application="MiuiCamera.apk" file="strings.xml" name="pref_camera_hdr_entryvalue_off"/>
	<item folder="all" application="MiuiCamera.apk" file="strings.xml" name="pref_camera_hdr_type_entryvalue_default"/>
	<item folder="all" application="MiuiCamera.apk" file="strings.xml" name="pref_camera_hdr_type_entryvalue_live"/>
	<item folder="all" application="MiuiCamera.apk" file="strings.xml" name="pref_camera_hdr_type_entryvalue_normal"/>
	<item folder="all" application="MiuiCamera.apk" file="strings.xml" name="pref_camera_hfr_default"/>
	<item folder="all" application="MiuiCamera.apk" file="strings.xml" name="pref_camera_hfr_value_2x"/>
	<item folder="all" application="MiuiCamera.apk" file="strings.xml" name="pref_camera_hfr_value_3x"/>
	<item folder="all" application="MiuiCamera.apk" file="strings.xml" name="pref_camera_hfr_value_4x"/>
	<item folder="all" application="MiuiCamera.apk" file="strings.xml" name="pref_camera_hfr_value_off"/>
	<item folder="all" application="MiuiCamera.apk" file="strings.xml" name="pref_camera_histogram_default"/>
	<item folder="all" application="MiuiCamera.apk" file="strings.xml" name="pref_camera_histogram_value_disable"/>
	<item folder="all" application="MiuiCamera.apk" file="strings.xml" name="pref_camera_histogram_value_enable"/>
	<item folder="all" application="MiuiCamera.apk" file="strings.xml" name="pref_camera_id_default"/>
	<item folder="all" application="MiuiCamera.apk" file="strings.xml" name="pref_camera_iso_default"/>
	<item folder="all" application="MiuiCamera.apk" file="strings.xml" name="pref_camera_iso_value_auto"/>
	<item folder="all" application="MiuiCamera.apk" file="strings.xml" name="pref_camera_iso_value_iso100"/>
	<item folder="all" application="MiuiCamera.apk" file="strings.xml" name="pref_camera_iso_value_iso1600"/>
	<item folder="all" application="MiuiCamera.apk" file="strings.xml" name="pref_camera_iso_value_iso200"/>
	<item folder="all" application="MiuiCamera.apk" file="strings.xml" name="pref_camera_iso_value_iso3200"/>
	<item folder="all" application="MiuiCamera.apk" file="strings.xml" name="pref_camera_iso_value_iso400"/>
	<item folder="all" application="MiuiCamera.apk" file="strings.xml" name="pref_camera_iso_value_iso800"/>
	<item folder="all" application="MiuiCamera.apk" file="strings.xml" name="pref_camera_jpegquality_default"/>
	<item folder="all" application="MiuiCamera.apk" file="strings.xml" name="pref_camera_jpegquality_value_high"/>
	<item folder="all" application="MiuiCamera.apk" file="strings.xml" name="pref_camera_jpegquality_value_low"/>
	<item folder="all" application="MiuiCamera.apk" file="strings.xml" name="pref_camera_jpegquality_value_normal"/>
	<item folder="all" application="MiuiCamera.apk" file="strings.xml" name="pref_camera_long_press_shutter_feature_default"/>
	<item folder="all" application="MiuiCamera.apk" file="strings.xml" name="pref_camera_long_pressing_burst_shooting_default"/>
	<item folder="all" application="MiuiCamera.apk" file="strings.xml" name="pref_camera_movie_solid_default"/>
	<item folder="all" application="MiuiCamera.apk" file="strings.xml" name="pref_camera_movie_solid_value_off"/>
	<item folder="all" application="MiuiCamera.apk" file="strings.xml" name="pref_camera_movie_solid_value_on"/>
	<item folder="all" application="MiuiCamera.apk" file="strings.xml" name="pref_camera_multiple_face_beauty_default"/>
	<item folder="all" application="MiuiCamera.apk" file="strings.xml" name="pref_camera_multiple_face_beauty_values_off"/>
	<item folder="all" application="MiuiCamera.apk" file="strings.xml" name="pref_camera_multiple_face_beauty_values_on"/>
	<item folder="all" application="MiuiCamera.apk" file="strings.xml" name="pref_camera_peak_default"/>
	<item folder="all" application="MiuiCamera.apk" file="strings.xml" name="pref_camera_picture_format_default"/>
	<item folder="all" application="MiuiCamera.apk" file="strings.xml" name="pref_camera_picture_format_value_jpeg"/>
	<item folder="all" application="MiuiCamera.apk" file="strings.xml" name="pref_camera_picture_format_value_raw"/>
	<item folder="all" application="MiuiCamera.apk" file="strings.xml" name="pref_camera_picture_size_default"/>
	<item folder="all" application="MiuiCamera.apk" file="strings.xml" name="pref_camera_picture_size_default_hm2"/>
	<item folder="all" application="MiuiCamera.apk" file="strings.xml" name="pref_camera_picture_size_default_hm2a"/>
	<item folder="all" application="MiuiCamera.apk" file="strings.xml" name="pref_camera_powermode_default"/>
	<item folder="all" application="MiuiCamera.apk" file="strings.xml" name="pref_camera_recordlocation_default"/>
	<item folder="all" application="MiuiCamera.apk" file="strings.xml" name="pref_camera_redeyereduction_default"/>
	<item folder="all" application="MiuiCamera.apk" file="strings.xml" name="pref_camera_referenceline_entryvalue_default"/>
	<item folder="all" application="MiuiCamera.apk" file="strings.xml" name="pref_camera_referenceline_entryvalue_off"/>
	<item folder="all" application="MiuiCamera.apk" file="strings.xml" name="pref_camera_referenceline_entryvalue_on"/>
	<item folder="all" application="MiuiCamera.apk" file="strings.xml" name="pref_camera_saturation_cm_test_default"/>
	<item folder="all" application="MiuiCamera.apk" file="strings.xml" name="pref_camera_saturation_default"/>
	<item folder="all" application="MiuiCamera.apk" file="strings.xml" name="pref_camera_scenedetect_default"/>
	<item folder="all" application="MiuiCamera.apk" file="strings.xml" name="pref_camera_scenemode_default"/>
	<item folder="all" application="MiuiCamera.apk" file="strings.xml" name="pref_camera_selectablezoneaf_default"/>
	<item folder="all" application="MiuiCamera.apk" file="strings.xml" name="pref_camera_setting_switch_default"/>
	<item folder="all" application="MiuiCamera.apk" file="strings.xml" name="pref_camera_setting_switch_entryvalue_off"/>
	<item folder="all" application="MiuiCamera.apk" file="strings.xml" name="pref_camera_setting_switch_entryvalue_on"/>
	<item folder="all" application="MiuiCamera.apk" file="strings.xml" name="pref_camera_shader_coloreffect_default"/>
	<item folder="all" application="MiuiCamera.apk" file="strings.xml" name="pref_camera_sharpness_default"/>
	<item folder="all" application="MiuiCamera.apk" file="strings.xml" name="pref_camera_show_gender_age_default"/>
	<item folder="all" application="MiuiCamera.apk" file="strings.xml" name="pref_camera_skin_beautify_default"/>
	<item folder="all" application="MiuiCamera.apk" file="strings.xml" name="pref_camera_skinToneEnhancement_default"/>
	<item folder="all" application="MiuiCamera.apk" file="strings.xml" name="pref_camera_skinToneEnhancement_value_auto"/>
	<item folder="all" application="MiuiCamera.apk" file="strings.xml" name="pref_camera_skinToneEnhancement_value_disable"/>
	<item folder="all" application="MiuiCamera.apk" file="strings.xml" name="pref_camera_skinToneEnhancement_value_enable"/>
	<item folder="all" application="MiuiCamera.apk" file="strings.xml" name="pref_camera_sound_default"/>
	<item folder="all" application="MiuiCamera.apk" file="strings.xml" name="pref_camera_sound_entryvalue_off"/>
	<item folder="all" application="MiuiCamera.apk" file="strings.xml" name="pref_camera_sound_entryvalue_on"/>
	<item folder="all" application="MiuiCamera.apk" file="strings.xml" name="pref_camera_touchafaec_default"/>
	<item folder="all" application="MiuiCamera.apk" file="strings.xml" name="pref_camera_video_duration_default"/>
	<item folder="all" application="MiuiCamera.apk" file="strings.xml" name="pref_camera_video_flashmode_default"/>
	<item folder="all" application="MiuiCamera.apk" file="strings.xml" name="pref_camera_videoencoder_default"/>
	<item folder="all" application="MiuiCamera.apk" file="strings.xml" name="pref_camera_volumekey_function_default"/>
	<item folder="all" application="MiuiCamera.apk" file="strings.xml" name="pref_camera_volumekey_function_entryvalue_exposure"/>
	<item folder="all" application="MiuiCamera.apk" file="strings.xml" name="pref_camera_volumekey_function_entryvalue_shutter"/>
	<item folder="all" application="MiuiCamera.apk" file="strings.xml" name="pref_camera_volumekey_function_entryvalue_volume"/>
	<item folder="all" application="MiuiCamera.apk" file="strings.xml" name="pref_camera_volumekey_function_entryvalue_zoom"/>
	<item folder="all" application="MiuiCamera.apk" file="strings.xml" name="pref_camera_watermark_default"/>
	<item folder="all" application="MiuiCamera.apk" file="strings.xml" name="pref_camera_watermark_entryvalue_off"/>
	<item folder="all" application="MiuiCamera.apk" file="strings.xml" name="pref_camera_watermark_entryvalue_on"/>
	<item folder="all" application="MiuiCamera.apk" file="strings.xml" name="pref_camera_whitebalance_default"/>
	<item folder="all" application="MiuiCamera.apk" file="strings.xml" name="pref_camera_whitebalance_entryvalue_auto"/>
	<item folder="all" application="MiuiCamera.apk" file="strings.xml" name="pref_camera_whitebalance_entryvalue_cloudy"/>
	<item folder="all" application="MiuiCamera.apk" file="strings.xml" name="pref_camera_whitebalance_entryvalue_daylight"/>
	<item folder="all" application="MiuiCamera.apk" file="strings.xml" name="pref_camera_whitebalance_entryvalue_fluorescent"/>
	<item folder="all" application="MiuiCamera.apk" file="strings.xml" name="pref_camera_whitebalance_entryvalue_incandescent"/>
	<item folder="all" application="MiuiCamera.apk" file="strings.xml" name="pref_camera_whitebalance_entryvalue_manual"/>
	<item folder="all" application="MiuiCamera.apk" file="strings.xml" name="pref_camera_whitebalance_entryvalue_measure"/>
	<item folder="all" application="MiuiCamera.apk" file="strings.xml" name="pref_camera_zsl_default"/>
	<item folder="all" application="MiuiCamera.apk" file="strings.xml" name="pref_camera_zsl_value_off"/>
	<item folder="all" application="MiuiCamera.apk" file="strings.xml" name="pref_camera_zsl_value_on"/>
	<item folder="all" application="MiuiCamera.apk" file="strings.xml" name="pref_captrue_mirror_default"/>
	<item folder="all" application="MiuiCamera.apk" file="strings.xml" name="pref_captrue_mirror_value_off"/>
	<item folder="all" application="MiuiCamera.apk" file="strings.xml" name="pref_captrue_mirror_value_on"/>
	<item folder="all" application="MiuiCamera.apk" file="strings.xml" name="pref_exposure_default"/>
	<item folder="all" application="MiuiCamera.apk" file="strings.xml" name="pref_face_beauty_default"/>
	<item folder="all" application="MiuiCamera.apk" file="strings.xml" name="pref_front_camera_delay_capture_default"/>
	<item folder="all" application="MiuiCamera.apk" file="strings.xml" name="pref_front_face_beauty_default"/>
	<item folder="all" application="MiuiCamera.apk" file="strings.xml" name="pref_front_mirror_default"/>
	<item folder="all" application="MiuiCamera.apk" file="strings.xml" name="pref_front_mirror_entryvalue_auto"/>
	<item folder="all" application="MiuiCamera.apk" file="strings.xml" name="pref_front_mirror_entryvalue_off"/>
	<item folder="all" application="MiuiCamera.apk" file="strings.xml" name="pref_front_mirror_entryvalue_on"/>
	<item folder="all" application="MiuiCamera.apk" file="strings.xml" name="pref_mi_front_video_quality_default"/>
	<item folder="all" application="MiuiCamera.apk" file="strings.xml" name="pref_mtk_camera_contrast_default"/>
	<item folder="all" application="MiuiCamera.apk" file="strings.xml" name="pref_mtk_camera_saturation_default"/>
	<item folder="all" application="MiuiCamera.apk" file="strings.xml" name="pref_mtk_camera_sharpness_default"/>
	<item folder="all" application="MiuiCamera.apk" file="strings.xml" name="pref_mtk_video_quality_default"/>
	<item folder="all" application="MiuiCamera.apk" file="strings.xml" name="pref_qc_focus_position_value_default"/>
	<item folder="all" application="MiuiCamera.apk" file="strings.xml" name="pref_scan_qrcode_default"/>
	<item folder="all" application="MiuiCamera.apk" file="strings.xml" name="pref_scan_qrcode_value_off"/>
	<item folder="all" application="MiuiCamera.apk" file="strings.xml" name="pref_scan_qrcode_value_on"/>
	<item folder="all" application="MiuiCamera.apk" file="strings.xml" name="pref_simple_hdr_default"/>
	<item folder="all" application="MiuiCamera.apk" file="strings.xml" name="pref_video_effect_default"/>
	<item folder="all" application="MiuiCamera.apk" file="strings.xml" name="pref_video_focusmode_entryvalue_auto"/>
	<item folder="all" application="MiuiCamera.apk" file="strings.xml" name="pref_video_focusmode_entryvalue_continuous"/>
	<item folder="all" application="MiuiCamera.apk" file="strings.xml" name="pref_video_focusmode_entryvalue_default"/>
	<item folder="all" application="MiuiCamera.apk" file="strings.xml" name="pref_video_quality_default"/>
	<item folder="all" application="MiuiCamera.apk" file="strings.xml" name="pref_video_quality_default_cmcc_test"/>
	<item folder="all" application="MiuiCamera.apk" file="strings.xml" name="pref_video_quality_entry_value_4kuhd"/>
	<item folder="all" application="MiuiCamera.apk" file="strings.xml" name="pref_video_quality_pad_default"/>
	<item folder="all" application="MiuiCamera.apk" file="strings.xml" name="pref_video_speed_default"/>
	<item folder="all" application="MiuiCamera.apk" file="strings.xml" name="pref_video_speed_value_fast"/>
	<item folder="all" application="MiuiCamera.apk" file="strings.xml" name="pref_video_speed_value_normal"/>
	<item folder="all" application="MiuiCamera.apk" file="strings.xml" name="pref_video_speed_value_slow"/>
	<item folder="all" application="MiuiCamera.apk" file="strings.xml" name="pref_video_time_lapse_frame_interval_default"/>
	<item folder="all" application="MiuiCamera.apk" file="strings.xml" name="setting_off_value"/>
	<item folder="all" application="MiuiCamera.apk" file="strings.xml" name="setting_on_value"/>
	<item folder="all" application="MiuiGallery.apk" file="strings.xml" name="camera_path"/>
	<item folder="all" application="MiuiGallery.apk" file="strings.xml" name="camera360_sdk_key"/>
	<item folder="all" application="MiuiGallery.apk" file="strings.xml" name="face_recommend_group_number"/>
	<item folder="all" application="MiuiGallery.apk" file="strings.xml" name="fileSizeSuffix"/>
	<item folder="all" application="MiuiGallery.apk" file="strings.xml" name="grant_permission_item"/>
	<item folder="all" application="MiuiGallery.apk" file="strings.xml" name="percent_sign"/>
	<item folder="all" application="MiuiGallery.apk" file="strings.xml" name="search_feedback_task_progress"/>
	<item folder="all" application="MiuiGallery.apk" file="strings.xml" name="search_transition_element_icon"/>
	<item folder="all" application="MiuiGallery.apk" file="strings.xml" name="search_transition_element_input"/>
	<item folder="all" application="MiuiHome.apk" file="strings.xml" name="home_indicator"/>
	<item folder="all" application="MiuiHome.apk" file="strings.xml" name="wallpaper_scrolling"/>
	<item folder="all" application="MiuiPackageInstaller.apk" file="strings.xml" name="power_charging"/>
	<item folder="all" application="MiuiPackageInstaller.apk" file="strings.xml" name="power_charging_duration_ac_short"/>
	<item folder="all" application="MiuiPackageInstaller.apk" file="strings.xml" name="power_charging_duration_short"/>
	<item folder="all" application="MiuiPackageInstaller.apk" file="strings.xml" name="power_charging_duration_usb_short"/>
	<item folder="all" application="MiuiPackageInstaller.apk" file="strings.xml" name="power_charging_duration_wireless_short"/>
	<item folder="all" application="MiuiPackageInstaller.apk" file="strings.xml" name="proxy_exclusionlist_hint"/>
	<item folder="all" application="MiuiPackageInstaller.apk" file="strings.xml" name="proxy_hostname_hint"/>
	<item folder="all" application="MiuiPackageInstaller.apk" file="strings.xml" name="proxy_port_hint"/>
	<item folder="all" application="MiuiPackageInstaller.apk" file="strings.xml" name="proxy_url_hint"/>
	<item folder="all" application="MiuiPackageInstaller.apk" file="strings.xml" name="wifi_dns1_hint"/>
	<item folder="all" application="MiuiPackageInstaller.apk" file="strings.xml" name="wifi_dns2_hint"/>
	<item folder="all" application="MiuiPackageInstaller.apk" file="strings.xml" name="wifi_gateway_hint"/>
	<item folder="all" application="MiuiPackageInstaller.apk" file="strings.xml" name="wifi_ip_address_hint"/>
	<item folder="all" application="MiuiPackageInstaller.apk" file="strings.xml" name="wifi_network_prefix_length_hint"/>
	<item folder="all" application="MiuiScanner.apk" file="strings.xml" name="document_ocr_language_key"/>
	<item folder="all" application="MiuiSystemUI.apk" file="strings.xml" name="network_speed_suffix"/>
	<item folder="all" application="MiuiSystemUI.apk" file="strings.xml" name="power_charging"/>
	<item folder="all" application="MiuiSystemUI.apk" file="strings.xml" name="power_charging_duration_ac_short"/>
	<item folder="all" application="MiuiSystemUI.apk" file="strings.xml" name="power_charging_duration_short"/>
	<item folder="all" application="MiuiSystemUI.apk" file="strings.xml" name="power_charging_duration_usb_short"/>
	<item folder="all" application="MiuiSystemUI.apk" file="strings.xml" name="power_charging_duration_wireless_short"/>
	<item folder="all" application="MiuiSystemUI.apk" file="strings.xml" name="proxy_exclusionlist_hint"/>
	<item folder="all" application="MiuiSystemUI.apk" file="strings.xml" name="proxy_hostname_hint"/>
	<item folder="all" application="MiuiSystemUI.apk" file="strings.xml" name="proxy_port_hint"/>
	<item folder="all" application="MiuiSystemUI.apk" file="strings.xml" name="proxy_url_hint"/>
	<item folder="all" application="MiuiSystemUI.apk" file="strings.xml" name="status_bar_date_formatter"/>
	<item folder="all" application="MiuiSystemUI.apk" file="strings.xml" name="status_bar_settings_battery_meter_format"/>
	<item folder="all" application="MiuiSystemUI.apk" file="strings.xml" name="weather_description_no_aqi"/>
	<item folder="all" application="MiuiVideo.apk" file="strings.xml" name="character_counter_pattern"/>
	<item folder="all" application="MiuiVideo.apk" file="strings.xml" name="file_match_detail"/>
	<item folder="all" application="MiuiVideo.apk" file="strings.xml" name="google_api_key"/>
	<item folder="all" application="MiuiVideo.apk" file="strings.xml" name="google_app_id"/>
	<item folder="all" application="MiuiVideo.apk" file="strings.xml" name="google_crash_reporting_api_key"/>
	<item folder="all" application="MiuiVideo.apk" file="strings.xml" name="send_video_type"/>
	<item folder="all" application="Mms.apk" file="strings.xml" name="flatshow_page_no"/>
	<item folder="all" application="Mms.apk" file="strings.xml" name="prefDefault_vibrate_false"/>
	<item folder="all" application="Mms.apk" file="strings.xml" name="prefDefault_vibrate_true"/>
	<item folder="all" application="Mms.apk" file="strings.xml" name="prefDefault_vibrateWhen"/>
	<item folder="all" application="Mms.apk" file="strings.xml" name="send_to_index_contact"/>
	<item folder="all" application="Music.apk" file="strings.xml" name="download_percent"/>
	<item folder="all" application="Music.apk" file="strings.xml" name="durationformatlong"/>
	<item folder="all" application="Music.apk" file="strings.xml" name="durationformatshort"/>
	<item folder="all" application="Music.apk" file="strings.xml" name="durationformatshort_padding_with_0"/>
	<item folder="all" application="Music.apk" file="strings.xml" name="listview_index_of_total"/>
	<item folder="all" application="Notes.apk" file="strings.xml" name="micloud_state_total_count"/>
	<item folder="all" application="PackageInstaller.apk" file="strings.xml" name="power_charging"/>
	<item folder="all" application="PackageInstaller.apk" file="strings.xml" name="power_charging_duration_ac_short"/>
	<item folder="all" application="PackageInstaller.apk" file="strings.xml" name="power_charging_duration_short"/>
	<item folder="all" application="PackageInstaller.apk" file="strings.xml" name="power_charging_duration_usb_short"/>
	<item folder="all" application="PackageInstaller.apk" file="strings.xml" name="power_charging_duration_wireless_short"/>
	<item folder="all" application="PackageInstaller.apk" file="strings.xml" name="proxy_exclusionlist_hint"/>
	<item folder="all" application="PackageInstaller.apk" file="strings.xml" name="proxy_hostname_hint"/>
	<item folder="all" application="PackageInstaller.apk" file="strings.xml" name="proxy_port_hint"/>
	<item folder="all" application="PackageInstaller.apk" file="strings.xml" name="proxy_url_hint"/>
	<item folder="all" application="PersonalAssistant.apk" file="arrays.xml" name="alipay_msp_image_loader_view_tag"/>
	<item folder="all" application="PersonalAssistant.apk" file="arrays.xml" name="alipay_msp_tag_view_holder"/>
	<item folder="all" application="PersonalAssistant.apk" file="arrays.xml" name="alipay_msp_view_wrapper"/>
	<item folder="all" application="PersonalAssistant.apk" file="arrays.xml" name="default_app"/>
	<item folder="all" application="PersonalAssistant.apk" file="arrays.xml" name="express_watched_app"/>
	<item folder="all" application="PersonalAssistant.apk" file="arrays.xml" name="express_watched_app_order_number_id"/>
	<item folder="all" application="PersonalAssistant.apk" file="arrays.xml" name="express_watched_app_company_id"/>
	<item folder="all" application="PersonalAssistant.apk" file="arrays.xml" name="alipay_CountryCodes"/>
	<item folder="all" application="PersonalAssistant.apk" file="strings.xml" name="alipay_msp_image_loader_view_tag"/>
	<item folder="all" application="PersonalAssistant.apk" file="strings.xml" name="alipay_msp_tag_view_holder"/>
	<item folder="all" application="PersonalAssistant.apk" file="strings.xml" name="alipay_msp_view_wrapper"/>
	<item folder="all" application="PersonalAssistant.apk" file="strings.xml" name="alipay_phoneNumber"/>
	<item folder="all" application="PersonalAssistant.apk" file="strings.xml" name="express_complete_flag"/>
	<item folder="all" application="PersonalAssistant.apk" file="strings.xml" name="express_delivery_flag"/>
	<item folder="all" application="PersonalAssistant.apk" file="strings.xml" name="info_divider"/>
	<item folder="all" application="PersonalAssistant.apk" file="strings.xml" name="keyboard_more_abc"/>
	<item folder="all" application="PersonalAssistant.apk" file="strings.xml" name="keyboard_more_num"/>
	<item folder="all" application="PersonalAssistant.apk" file="strings.xml" name="msp_mini_layout"/>
	<item folder="all" application="PersonalAssistant.apk" file="strings.xml" name="msp_mini_layout_parent"/>
	<item folder="all" application="PersonalAssistant.apk" file="strings.xml" name="msp_mini_linblocksconpent"/>
	<item folder="all" application="PersonalAssistant.apk" file="strings.xml" name="msp_mini_root"/>
	<item folder="all" application="PersonalAssistant.apk" file="strings.xml" name="payment_amount_empty"/>
	<item folder="all" application="PersonalAssistant.apk" file="strings.xml" name="personalAssistant_path"/>
	<item folder="all" application="PersonalAssistant.apk" file="strings.xml" name="stock_change_rate_format"/>
	<item folder="all" application="PersonalAssistant.apk" file="strings.xml" name="tag_view_nav"/>
	<item folder="all" application="PersonalAssistantPlugin.apk" file="arrays.xml" name="express_status_detail_flag"/>
	<item folder="all" application="PersonalAssistantPlugin.apk" file="arrays.xml" name="express_status_flag_all"/>
	<item folder="all" application="PersonalAssistantPlugin.apk" file="strings.xml" name="express_complete_flag"/>
	<item folder="all" application="PersonalAssistantPlugin.apk" file="strings.xml" name="express_delivery_flag"/>
	<item folder="all" application="PersonalAssistantPlugin.apk" file="strings.xml" name="personalAssistant_path"/>
	<item folder="all" application="PersonalAssistantPlugin.apk" file="strings.xml" name="stock_change_rate_format"/>
	<item folder="all" application="PrintSpooler.apk" file="strings.xml" name="current_page_template"/>
	<item folder="all" application="PrintSpooler.apk" file="strings.xml" name="printer_extended_description_template"/>
	<item folder="all" application="PowerKeeper.apk" file="arrays.xml" name="action_name"/>
	<item folder="all" application="PowerKeeper.apk" file="arrays.xml" name="action_param"/>
	<item folder="all" application="PowerKeeper.apk" file="arrays.xml" name="alarm_general_type_restricted"/>
	<item folder="all" application="PowerKeeper.apk" file="arrays.xml" name="broadcast_general_type_restricted"/>
	<item folder="all" application="PowerKeeper.apk" file="arrays.xml" name="cpu_actions_device"/>
	<item folder="all" application="PowerKeeper.apk" file="arrays.xml" name="event_name"/>
	<item folder="all" application="PowerKeeper.apk" file="arrays.xml" name="group_name"/>
	<item folder="all" application="PowerKeeper.apk" file="arrays.xml" name="read_disable"/>
	<item folder="all" application="PowerKeeper.apk" file="arrays.xml" name="shown_action_name"/>
	<item folder="all" application="PowerKeeper.apk" file="arrays.xml" name="shown_mandatory_event_name"/>
	<item folder="all" application="PowerKeeper.apk" file="arrays.xml" name="shown_optional_event_name"/>
	<item folder="all" application="SecurityAdd.apk" file="strings.xml" name="preference_key_information_setting_close"/>
	<item folder="all" application="SecurityAdd.apk" file="strings.xml" name="preference_key_information_setting_wlan"/>
	<item folder="all" application="SecurityCenter.apk" file="arrays.xml" name="st_antispam_mode_defined_state"/>
	<item folder="all" application="SecurityCenter.apk" file="arrays.xml" name="st_antispam_mode_defined_state_international"/>
	<item folder="all" application="SecurityCenter.apk" file="strings.xml" name="category_key_power_usage_details"/>
	<item folder="all" application="SecurityCenter.apk" file="strings.xml" name="category_key_power_usage_packages"/>
	<item folder="all" application="SecurityCenter.apk" file="strings.xml" name="create_table_keyword"/>
	<item folder="all" application="SecurityCenter.apk" file="strings.xml" name="create_table_mode"/>
	<item folder="all" application="SecurityCenter.apk" file="strings.xml" name="create_table_phonelist"/>
	<item folder="all" application="SecurityCenter.apk" file="strings.xml" name="create_table_report_sms"/>
	<item folder="all" application="SecurityCenter.apk" file="strings.xml" name="create_table_report_sms_pending"/>
	<item folder="all" application="SecurityCenter.apk" file="strings.xml" name="create_table_sim"/>
	<item folder="all" application="SecurityCenter.apk" file="strings.xml" name="create_talbe_fwlog"/>
	<item folder="all" application="SecurityCenter.apk" file="strings.xml" name="dynamic_md5"/>
	<item folder="all" application="SecurityCenter.apk" file="strings.xml" name="menu_text_networkassistants_data"/>
	<item folder="all" application="SecurityCenter.apk" file="strings.xml" name="om_memory_clean_memory_info_text"/>
	<item folder="all" application="SecurityCenter.apk" file="strings.xml" name="pref_operator_setting"/>
	<item folder="all" application="SecurityCenter.apk" file="strings.xml" name="preference_category_information_setting"/>
	<item folder="all" application="SecurityCenter.apk" file="strings.xml" name="preference_category_key_reference_settings"/>
	<item folder="all" application="SecurityCenter.apk" file="strings.xml" name="preference_category_key_virus_lib_auto_update"/>
	<item folder="all" application="SecurityCenter.apk" file="strings.xml" name="preference_category_key_virus_white_list"/>
	<item folder="all" application="SecurityCenter.apk" file="strings.xml" name="preference_key_information_setting_close"/>
	<item folder="all" application="SecurityCenter.apk" file="strings.xml" name="preference_key_information_setting_wlan"/>
	<item folder="all" application="SecurityCenter.apk" file="strings.xml" name="st_antispam_mode_blacklist_state"/>
	<item folder="all" application="SecurityCenter.apk" file="strings.xml" name="st_antispam_mode_only_all_deny_state"/>
	<item folder="all" application="SecurityCenter.apk" file="strings.xml" name="st_antispam_mode_only_contacts_state"/>
	<item folder="all" application="SecurityCenter.apk" file="strings.xml" name="st_antispam_mode_only_whitelist_state"/>
	<item folder="all" application="SecurityCenter.apk" file="strings.xml" name="st_antispam_mode_smart_state"/>
	<item folder="all" application="SecurityCenter.apk" file="strings.xml" name="xiaomi_account_type"/>
	<item folder="all" application="Settings.apk" file="arrays.xml" name="always_enabled_app_list"/>
	<item folder="all" application="Settings.apk" file="arrays.xml" name="change_security_lock_picker_key"/>
	<item folder="all" application="Settings.apk" file="arrays.xml" name="key_and_gesture_shortcut_action"/>
	<item folder="all" application="Settings.apk" file="arrays.xml" name="standard_configuration_version_description_secondary"/>
	<item folder="all" application="Settings.apk" file="strings.xml" name="call_manager_summary"/>
	<item folder="all" application="Settings.apk" file="strings.xml" name="dndm_auto_time_setting_summary"/>
	<item folder="all" application="Settings.apk" file="strings.xml" name="gadget_state_template"/>
	<item folder="all" application="Settings.apk" file="strings.xml" name="link_speed"/>
	<item folder="all" application="Settings.apk" file="strings.xml" name="memory_use_running_format"/>
	<item folder="all" application="Settings.apk" file="strings.xml" name="misc_files_selected_count_bytes"/>
	<item folder="all" application="Settings.apk" file="strings.xml" name="nfc_payment_app_and_desc"/>
	<item folder="all" application="Settings.apk" file="strings.xml" name="night_mode_summary"/>
	<item folder="all" application="Settings.apk" file="strings.xml" name="notifications_three_items"/>
	<item folder="all" application="Settings.apk" file="strings.xml" name="notifications_two_items"/>
	<item folder="all" application="Settings.apk" file="strings.xml" name="owner_info_settings_status"/>
	<item folder="all" application="Settings.apk" file="strings.xml" name="physical_device_title"/>
	<item folder="all" application="Settings.apk" file="strings.xml" name="power_charging"/>
	<item folder="all" application="Settings.apk" file="strings.xml" name="power_charging_duration_ac_short"/>
	<item folder="all" application="Settings.apk" file="strings.xml" name="power_charging_duration_short"/>
	<item folder="all" application="Settings.apk" file="strings.xml" name="power_charging_duration_usb_short"/>
	<item folder="all" application="Settings.apk" file="strings.xml" name="power_charging_duration_wireless_short"/>
	<item folder="all" application="Settings.apk" file="strings.xml" name="process_format"/>
	<item folder="all" application="Settings.apk" file="strings.xml" name="proxy_exclusionlist_hint"/>
	<item folder="all" application="Settings.apk" file="strings.xml" name="proxy_hostname_hint"/>
	<item folder="all" application="Settings.apk" file="strings.xml" name="proxy_port_hint"/>
	<item folder="all" application="Settings.apk" file="strings.xml" name="proxy_url_hint"/>
	<item folder="all" application="Settings.apk" file="strings.xml" name="service_client_name"/>
	<item folder="all" application="Settings.apk" file="strings.xml" name="service_process_name"/>
	<item folder="all" application="Settings.apk" file="strings.xml" name="sim_settings_summary"/>
	<item folder="all" application="Settings.apk" file="strings.xml" name="size_suffix"/>
	<item folder="all" application="Settings.apk" file="strings.xml" name="summary_font_size"/>
	<item folder="all" application="Settings.apk" file="strings.xml" name="summary_range_symbol_combination"/>
	<item folder="all" application="Settings.apk" file="strings.xml" name="sync_item_title"/>
	<item folder="all" application="Settings.apk" file="strings.xml" name="tune_away_Default"/>
	<item folder="all" application="Settings.apk" file="strings.xml" name="zen_mode_rule_summary_combination"/>
	<item folder="all" application="Settings.apk" file="strings.xml" name="zen_mode_summary_combination"/>
	<item folder="all" application="SettingsProvider.apk" file="strings.xml" name="airplane_mode_toggleable_radios"/>
	<item folder="all" application="SettingsProvider.apk" file="strings.xml" name="def_backup_transport"/>
	<item folder="all" application="SoundRecorder.apk" file="strings.xml" name="xiaomi_account_type"/>
	<item folder="all" application="Telecom.apk" file="strings.xml" name="default_connection_manager_component"/>
	<item folder="all" application="Telecom.apk" file="strings.xml" name="dialer_default_class"/>
	<item folder="all" application="Telecom.apk" file="strings.xml" name="incall_default_class"/>
	<item folder="all" application="Telecom.apk" file="strings.xml" name="Lch_dtmf_key"/>
	<item folder="all" application="Telecom.apk" file="strings.xml" name="power_charging"/>
	<item folder="all" application="Telecom.apk" file="strings.xml" name="power_charging_duration_ac_short"/>
	<item folder="all" application="Telecom.apk" file="strings.xml" name="power_charging_duration_short"/>
	<item folder="all" application="Telecom.apk" file="strings.xml" name="power_charging_duration_usb_short"/>
	<item folder="all" application="Telecom.apk" file="strings.xml" name="power_charging_duration_wireless_short"/>
	<item folder="all" application="Telecom.apk" file="strings.xml" name="proxy_exclusionlist_hint"/>
	<item folder="all" application="Telecom.apk" file="strings.xml" name="proxy_hostname_hint"/>
	<item folder="all" application="Telecom.apk" file="strings.xml" name="proxy_port_hint"/>
	<item folder="all" application="Telecom.apk" file="strings.xml" name="proxy_url_hint"/>
	<item folder="all" application="Telecom.apk" file="strings.xml" name="ui_default_package"/>
	<item folder="all" application="Telecom.apk" file="strings.xml" name="ui_default_package_dialer"/>
	<item folder="all" application="TeleService.apk" file="arrays.xml" name="absent_num"/>
	<item folder="all" application="TeleService.apk" file="strings.xml" name="advanced_settings_container"/>
	<item folder="all" application="TeleService.apk" file="strings.xml" name="auth_username"/>
	<item folder="all" application="TeleService.apk" file="strings.xml" name="default_port"/>
	<item folder="all" application="TeleService.apk" file="strings.xml" name="default_transport"/>
	<item folder="all" application="TeleService.apk" file="strings.xml" name="display_name"/>
	<item folder="all" application="TeleService.apk" file="strings.xml" name="domain_address"/>
	<item folder="all" application="TeleService.apk" file="strings.xml" name="password"/>
	<item folder="all" application="TeleService.apk" file="strings.xml" name="port"/>
	<item folder="all" application="TeleService.apk" file="strings.xml" name="power_charging"/>
	<item folder="all" application="TeleService.apk" file="strings.xml" name="power_charging_duration_ac_short"/>
	<item folder="all" application="TeleService.apk" file="strings.xml" name="power_charging_duration_short"/>
	<item folder="all" application="TeleService.apk" file="strings.xml" name="power_charging_duration_usb_short"/>
	<item folder="all" application="TeleService.apk" file="strings.xml" name="power_charging_duration_wireless_short"/>
	<item folder="all" application="TeleService.apk" file="strings.xml" name="proxy_exclusionlist_hint"/>
	<item folder="all" application="TeleService.apk" file="strings.xml" name="proxy_hostname_hint"/>
	<item folder="all" application="TeleService.apk" file="strings.xml" name="proxy_port_hint"/>
	<item folder="all" application="TeleService.apk" file="strings.xml" name="proxy_url_hint"/>
	<item folder="all" application="TeleService.apk" file="strings.xml" name="send_keepalive"/>
	<item folder="all" application="TeleService.apk" file="strings.xml" name="set_primary"/>
	<item folder="all" application="TeleService.apk" file="strings.xml" name="sip_address_only"/>
	<item folder="all" application="TeleService.apk" file="strings.xml" name="sip_always"/>
	<item folder="all" application="TeleService.apk" file="strings.xml" name="sip_ask_me_each_time"/>
	<item folder="all" application="TeleService.apk" file="strings.xml" name="transport"/>
	<item folder="all" application="TeleService.apk" file="strings.xml" name="username"/>
	<item folder="all" application="TeleService.apk" file="strings.xml" name="voicemail_notification_vibrate_when_default"/>
	<item folder="all" application="ThemeManager.apk" file="strings.xml" name="gift_count_format"/>
	<item folder="all" application="ThemeManager.apk" file="strings.xml" name="theme_name"/>
	<item folder="all" application="Updater.apk" file="strings.xml" name="chengelog"/>
	<item folder="all" application="Weather.apk" file="strings.xml" name="daily_forecast_detail_date_format"/>
	<item folder="all" application="Weather.apk" file="strings.xml" name="data_source_time_fromat"/>
	<item folder="all" application="Weather.apk" file="strings.xml" name="hourly_forecast_bottom_aqi_chinese"/>
	<item folder="all" application="Weather.apk" file="strings.xml" name="hourly_forecast_bottom_aqi_else"/>
	<item folder="all" application="Weather.apk" file="strings.xml" name="indices_desc_humidity_without_pic"/>
	<item folder="all" application="Weather.apk" file="strings.xml" name="information_time_source"/>
	<item folder="all" application="Weather.apk" file="strings.xml" name="install_progress"/>
	<item folder="all" application="Weather.apk" file="strings.xml" name="international_details_wind_connect"/>
	<item folder="all" application="Weather.apk" file="strings.xml" name="share_weather_desc_alert"/>
	<item folder="all" application="XiaomiServiceFramework.apk" file="strings.xml" name="activate_sms_postfix"/>
	<item folder="all" application="XMRemoteController.apk" file="strings.xml" name="brand_device"/>
	<item folder="all" application="XMRemoteController.apk" file="strings.xml" name="character_counter_pattern"/>
	<item folder="all" application="XMRemoteController.apk" file="strings.xml" name="humidity_frame"/>
	<item folder="all" application="XMRemoteController.apk" file="strings.xml" name="lock_screen_device_sum"/>
	<item folder="all" application="XMRemoteController.apk" file="strings.xml" name="match_dataset_frame"/>
	<item folder="all" application="XMRemoteController.apk" file="strings.xml" name="scene_name_frame"/>
	<item folder="all" application="XMRemoteController.apk" file="strings.xml" name="scene_name_frame_short"/>
	<item folder="all" application="XMRemoteController.apk" file="strings.xml" name="stb_detail_title_frame"/>
	<item folder="all" application="XMRemoteController.apk" file="strings.xml" name="time_interval_in_sec"/>
	<item folder="all" application="XMRemoteController.apk" file="strings.xml" name="year_format"/>
	<item folder="all" application="YellowPage.apk" file="strings.xml" name="express_order_state"/>
	<item folder="all" application="YellowPage.apk" file="strings.xml" name="nearby_yellow_page_title_format"/>
	<item folder="all" application="YellowPage.apk" file="strings.xml" name="order_merchant_title_format"/>
	<item folder="all" application="YellowPage.apk" file="strings.xml" name="recharge_phone_format"/>
	<item folder="all" application="YellowPage.apk" file="strings.xml" name="shop_recommendation_format"/>
	<item folder="main" application="CABLService.apk" file="strings.xml" name="cabl_level_default"/>
	<item folder="main" application="MiuiSystemUI.apk" file="strings.xml" name="flash_device"/>
</recources>
